PyQt6/bindings/QHexEdit/QHexEdit.sip
PyQt6/bindings/QHexEdit/QHexEdit.toml
QHexEdit.cpython-312-x86_64-linux-gnu.so
pyqt6_qhexedit-0.9.0.dist-info/WHEEL
pyqt6_qhexedit-0.9.0.dist-info/METADATA
pyqt6_qhexedit-0.9.0.dist-info/RECORD
