Metadata-Version: 2.1
Name: PyQt6-QHexEdit
Version: 0.9.0
Requires-Python: >=3.8
Classifier: Development Status :: 5 - Production/Stable
Classifier: Environment :: X11 Applications :: Qt
Classifier: Intended Audience :: Developers
Classifier: Topic :: Software Development :: Embedded Systems
Classifier: Topic :: Utilities
Keywords: Development, Binary, Editor, Hex Editor, Viewer
Summary: Python bindings for the QHexEdit Widget
Project-Url: homepage, https://github.com/Simsys/qhexedit2
Requires-Dist: PyQt6-sip (>=13.8, <14)
Requires-Dist: PyQt6 (>=6.2.0)
License: LGPL-2.1-only
Author-Email: Winfried Simon <winfried.simon@gmail.com>
